odoo/addons/mrp_bom_current_stock/README.rst
odoo/addons/mrp_bom_current_stock/__init__.py
odoo/addons/mrp_bom_current_stock/__manifest__.py
odoo/addons/mrp_bom_current_stock/i18n/mrp_bom_current_stock.pot
odoo/addons/mrp_bom_current_stock/reports/report_mrpcurrentstock.xml
odoo/addons/mrp_bom_current_stock/static/description/icon.png
odoo/addons/mrp_bom_current_stock/wizard/__init__.py
odoo/addons/mrp_bom_current_stock/wizard/bom_route_current_stock.py
odoo/addons/mrp_bom_current_stock/wizard/bom_route_current_stock_view.xml
odoo11_addon_mrp_bom_current_stock-11.0.1.1.0.dist-info/METADATA
odoo11_addon_mrp_bom_current_stock-11.0.1.1.0.dist-info/RECORD
odoo11_addon_mrp_bom_current_stock-11.0.1.1.0.dist-info/WHEEL
odoo11_addon_mrp_bom_current_stock-11.0.1.1.0.dist-info/top_level.txt
